{
  "metadata": {
    "batch_name": "sample_video_1703123456",
    "source_video": "/home/user/videos/sample_video.mp4",
    "source_video_name": "sample_video.mp4",
    "created_at": "2024-01-20 15:30:56",
    "created_timestamp": 1703088656.0,
    "project_version": "1.0.0",
    "processing_status": "completed",
    "last_updated": "2024-01-20 15:43:30",
    "completed_at": "2024-01-20 15:43:30",
    "processing_duration_seconds": 754.0,
    "processing_duration_formatted": "12m 34s"
  },
  "video_properties": {
    "width": 1920,
    "height": 1080,
    "fps": 30.0,
    "frame_count": 1800,
    "duration": 60.0,
    "format": "mp4",
    "bitrate": 5000000
  },
  "processing_settings": {
    "baseline": 0.065,
    "focal_length": 1000,
    "vr_format": "side_by_side",
    "vr_resolution": "16x9-1080p",
    "processing_mode": "serial",
    "fisheye_projection": "stereographic",
    "fisheye_fov": 105,
    "crop_factor": 1.0,
    "fisheye_crop_factor": 1.0,
    "hole_fill_quality": "fast",
    "super_sample": "auto",
    "target_fps": 60,
    "min_resolution": "1080p",
    "preserve_audio": true,
    "keep_intermediates": true,
    "apply_distortion": true,
    "per_eye_width": 1920,
    "per_eye_height": 1080,
    "vr_output_width": 3840,
    "vr_output_height": 1080,
    "source_width": 1920,
    "source_height": 1080,
    "source_fps": 30.0
  },
  "output_info": {
    "output_directory": "/home/user/workspace/depth-surge-3d/output/sample_video_1703123456",
    "expected_output_filename": "sample_video_side-by-side_16x9-1080p_serial.mp4"
  },
  "runtime_info": {
    "final_output": "/home/user/workspace/depth-surge-3d/output/sample_video_1703123456/sample_video_side-by-side_16x9-1080p_serial.mp4",
    "frames_processed": 1800,
    "device_used": "cuda",
    "model_type": "vitl",
    "peak_memory_usage": "4.2 GB"
  }
} 